{
    "%vlocity_namespace%__Author__c": "COX",
    "%vlocity_namespace%__CardType__c": "flex",
    "%vlocity_namespace%__Datasource__c": {
        "contextVariables": [
        ],
        "orderBy": {
        },
        "type": null,
        "value": {
        }
    },
    "%vlocity_namespace%__Definition__c": "COXDB.json",
    "%vlocity_namespace%__Description__c": "",
    "%vlocity_namespace%__GlobalKey__c": "COXDB/COX/1/1646743241205",
    "%vlocity_namespace%__IsChildCard__c": false,
    "%vlocity_namespace%__ParentID__c": "UIBase/copado/4/1643259864511",
    "%vlocity_namespace%__SampleData__c": "",
    "%vlocity_namespace%__Styles__c": "",
    "%vlocity_namespace%__Type__c": "",
    "%vlocity_namespace%__Version__c": 1,
    "Name": "COXDB",
    "VlocityDataPackType": "SObject",
    "VlocityRecordSObjectType": "%vlocity_namespace%__VlocityCard__c",
    "VlocityRecordSourceKey": "%vlocity_namespace%__VlocityCard__c/COXDB"
}