[
    {
        "%vlocity_namespace%__DomainObjectAPIName__c": "json",
        "%vlocity_namespace%__DomainObjectCreationOrder__c": 0,
        "%vlocity_namespace%__DomainObjectFieldAPIName__c": "oi",
        "%vlocity_namespace%__FilterGroup__c": 0,
        "%vlocity_namespace%__FilterOperator__c": "=",
        "%vlocity_namespace%__GlobalKey__c": "66f6625e-d6d9-1772-e09f-ba1a9ffa626e",
        "%vlocity_namespace%__InterfaceFieldAPIName__c": "Id",
        "%vlocity_namespace%__InterfaceObjectLookupOrder__c": 1,
        "%vlocity_namespace%__InterfaceObjectName__c": "OrderItem",
        "%vlocity_namespace%__IsDisabled__c": false,
        "%vlocity_namespace%__IsRequiredForUpsert__c": false,
        "%vlocity_namespace%__MapId__c": "Alpha Confirm Resource RequestCustom9116",
        "%vlocity_namespace%__OMplusSyncEnabled__c": true,
        "%vlocity_namespace%__UpsertKey__c": false,
        "Name": "Alpha Confirm Resource Request",
        "VlocityDataPackType": "SObject",
        "VlocityRecordSObjectType": "%vlocity_namespace%__DRMapItem__c"
    },
    {
        "%vlocity_namespace%__DomainObjectAPIName__c": "json",
        "%vlocity_namespace%__DomainObjectCreationOrder__c": 1,
        "%vlocity_namespace%__DomainObjectFieldAPIName__c": "orderItemsWithAttrs:attrs:Reserve network resources",
        "%vlocity_namespace%__GlobalKey__c": "53d539a3-ac91-eaeb-a602-7ee50753c3c0",
        "%vlocity_namespace%__InterfaceFieldAPIName__c": "oi:AvailableQuantity",
        "%vlocity_namespace%__IsDisabled__c": false,
        "%vlocity_namespace%__IsRequiredForUpsert__c": false,
        "%vlocity_namespace%__MapId__c": "Alpha Confirm Resource RequestCustom7789",
        "%vlocity_namespace%__OMplusSyncEnabled__c": true,
        "%vlocity_namespace%__UpsertKey__c": false,
        "Name": "Alpha Confirm Resource Request",
        "VlocityDataPackType": "SObject",
        "VlocityRecordSObjectType": "%vlocity_namespace%__DRMapItem__c"
    },
    {
        "%vlocity_namespace%__DomainObjectAPIName__c": "json",
        "%vlocity_namespace%__DomainObjectCreationOrder__c": 1,
        "%vlocity_namespace%__DomainObjectFieldAPIName__c": "orderItemsWithAttrs:attrs:Service ID",
        "%vlocity_namespace%__GlobalKey__c": "a885593d-5471-69cb-782a-2ca0582f7594",
        "%vlocity_namespace%__InterfaceFieldAPIName__c": "oi:Id",
        "%vlocity_namespace%__IsDisabled__c": false,
        "%vlocity_namespace%__IsRequiredForUpsert__c": false,
        "%vlocity_namespace%__MapId__c": "Alpha Confirm Resource RequestCustom7625",
        "%vlocity_namespace%__OMplusSyncEnabled__c": true,
        "%vlocity_namespace%__UpsertKey__c": false,
        "Name": "Alpha Confirm Resource Request",
        "VlocityDataPackType": "SObject",
        "VlocityRecordSObjectType": "%vlocity_namespace%__DRMapItem__c"
    },
    {
        "%vlocity_namespace%__DomainObjectAPIName__c": "json",
        "%vlocity_namespace%__DomainObjectCreationOrder__c": 1,
        "%vlocity_namespace%__DomainObjectFieldAPIName__c": "orderItemsWithAttrs:attrs:Speed",
        "%vlocity_namespace%__GlobalKey__c": "979e6b1f-5a63-58ba-a266-260ee6ae0fbc",
        "%vlocity_namespace%__InterfaceFieldAPIName__c": "oi:%vlocity_namespace%__ValidationDate__c",
        "%vlocity_namespace%__IsDisabled__c": false,
        "%vlocity_namespace%__IsRequiredForUpsert__c": false,
        "%vlocity_namespace%__MapId__c": "Alpha Confirm Resource RequestCustom1343",
        "%vlocity_namespace%__OMplusSyncEnabled__c": true,
        "%vlocity_namespace%__UpsertKey__c": false,
        "Name": "Alpha Confirm Resource Request",
        "VlocityDataPackType": "SObject",
        "VlocityRecordSObjectType": "%vlocity_namespace%__DRMapItem__c"
    },
    {
        "%vlocity_namespace%__DomainObjectAPIName__c": "json",
        "%vlocity_namespace%__DomainObjectCreationOrder__c": 1,
        "%vlocity_namespace%__DomainObjectFieldAPIName__c": "orderItemsWithAttrs:id",
        "%vlocity_namespace%__GlobalKey__c": "c92d591d-47ee-2072-86db-8b74a9a035f3",
        "%vlocity_namespace%__InterfaceFieldAPIName__c": "oi:EndDate",
        "%vlocity_namespace%__IsDisabled__c": false,
        "%vlocity_namespace%__IsRequiredForUpsert__c": false,
        "%vlocity_namespace%__MapId__c": "Alpha Confirm Resource RequestCustom2371",
        "%vlocity_namespace%__OMplusSyncEnabled__c": true,
        "%vlocity_namespace%__UpsertKey__c": false,
        "Name": "Alpha Confirm Resource Request",
        "VlocityDataPackType": "SObject",
        "VlocityRecordSObjectType": "%vlocity_namespace%__DRMapItem__c"
    }
]