[
    {
        "%vlocity_namespace%__Abbreviation__c": "",
        "%vlocity_namespace%__BooleanValue__c": false,
        "%vlocity_namespace%__Code__c": "PKI_SP1",
        "%vlocity_namespace%__DateTimeValue__c": "",
        "%vlocity_namespace%__DateValue__c": "",
        "%vlocity_namespace%__EffectiveFromDate__c": "2022-05-31",
        "%vlocity_namespace%__EffectiveUntilDate__c": "",
        "%vlocity_namespace%__GlobalKey__c": "42264595-8e9d-8ba0-53da-bf7272199811",
        "%vlocity_namespace%__IsActive__c": true,
        "%vlocity_namespace%__IsDefault__c": false,
        "%vlocity_namespace%__NumberValue__c": "",
        "%vlocity_namespace%__PicklistId__c": {
            "%vlocity_namespace%__GlobalKey__c": "65ffc74b-9002-fc9d-e3a1-270126c262b9",
            "VlocityDataPackType": "VlocityMatchingKeyObject",
            "VlocityMatchingRecordSourceKey": "%vlocity_namespace%__Picklist__c/65ffc74b-9002-fc9d-e3a1-270126c262b9",
            "VlocityRecordSObjectType": "%vlocity_namespace%__Picklist__c"
        },
        "%vlocity_namespace%__Sequence__c": 10,
        "%vlocity_namespace%__TextValue__c": "SP1",
        "%vlocity_namespace%__UnitOfMeasureName__c": "",
        "%vlocity_namespace%__Value__c": "SP1",
        "Name": "SP1",
        "VlocityDataPackType": "SObject",
        "VlocityRecordSObjectType": "%vlocity_namespace%__PicklistValue__c",
        "VlocityRecordSourceKey": "%vlocity_namespace%__PicklistValue__c/42264595-8e9d-8ba0-53da-bf7272199811"
    },
    {
        "%vlocity_namespace%__Abbreviation__c": "",
        "%vlocity_namespace%__BooleanValue__c": false,
        "%vlocity_namespace%__Code__c": "PKI_SP2",
        "%vlocity_namespace%__DateTimeValue__c": "",
        "%vlocity_namespace%__DateValue__c": "",
        "%vlocity_namespace%__EffectiveFromDate__c": "2022-05-31",
        "%vlocity_namespace%__EffectiveUntilDate__c": "",
        "%vlocity_namespace%__GlobalKey__c": "ec2c5d44-73d9-4f6d-7a28-d8e0784a8491",
        "%vlocity_namespace%__IsActive__c": true,
        "%vlocity_namespace%__IsDefault__c": false,
        "%vlocity_namespace%__NumberValue__c": "",
        "%vlocity_namespace%__PicklistId__c": {
            "%vlocity_namespace%__GlobalKey__c": "65ffc74b-9002-fc9d-e3a1-270126c262b9",
            "VlocityDataPackType": "VlocityMatchingKeyObject",
            "VlocityMatchingRecordSourceKey": "%vlocity_namespace%__Picklist__c/65ffc74b-9002-fc9d-e3a1-270126c262b9",
            "VlocityRecordSObjectType": "%vlocity_namespace%__Picklist__c"
        },
        "%vlocity_namespace%__Sequence__c": 20,
        "%vlocity_namespace%__TextValue__c": "SP2",
        "%vlocity_namespace%__UnitOfMeasureName__c": "",
        "%vlocity_namespace%__Value__c": "SP2",
        "Name": "SP2",
        "VlocityDataPackType": "SObject",
        "VlocityRecordSObjectType": "%vlocity_namespace%__PicklistValue__c",
        "VlocityRecordSourceKey": "%vlocity_namespace%__PicklistValue__c/ec2c5d44-73d9-4f6d-7a28-d8e0784a8491"
    },
    {
        "%vlocity_namespace%__Abbreviation__c": "",
        "%vlocity_namespace%__BooleanValue__c": false,
        "%vlocity_namespace%__Code__c": "PKI_SP3",
        "%vlocity_namespace%__DateTimeValue__c": "",
        "%vlocity_namespace%__DateValue__c": "",
        "%vlocity_namespace%__EffectiveFromDate__c": "2022-05-31",
        "%vlocity_namespace%__EffectiveUntilDate__c": "",
        "%vlocity_namespace%__GlobalKey__c": "c23b3d22-914e-135d-462d-d3a89f413986",
        "%vlocity_namespace%__IsActive__c": true,
        "%vlocity_namespace%__IsDefault__c": false,
        "%vlocity_namespace%__NumberValue__c": "",
        "%vlocity_namespace%__PicklistId__c": {
            "%vlocity_namespace%__GlobalKey__c": "65ffc74b-9002-fc9d-e3a1-270126c262b9",
            "VlocityDataPackType": "VlocityMatchingKeyObject",
            "VlocityMatchingRecordSourceKey": "%vlocity_namespace%__Picklist__c/65ffc74b-9002-fc9d-e3a1-270126c262b9",
            "VlocityRecordSObjectType": "%vlocity_namespace%__Picklist__c"
        },
        "%vlocity_namespace%__Sequence__c": 30,
        "%vlocity_namespace%__TextValue__c": "SP3",
        "%vlocity_namespace%__UnitOfMeasureName__c": "",
        "%vlocity_namespace%__Value__c": "SP3",
        "Name": "SP3",
        "VlocityDataPackType": "SObject",
        "VlocityRecordSObjectType": "%vlocity_namespace%__PicklistValue__c",
        "VlocityRecordSourceKey": "%vlocity_namespace%__PicklistValue__c/c23b3d22-914e-135d-462d-d3a89f413986"
    }
]