[
    {
        "%vlocity_namespace%__DomainObjectAPIName__c": "json",
        "%vlocity_namespace%__DomainObjectCreationOrder__c": 0,
        "%vlocity_namespace%__DomainObjectFieldAPIName__c": "Order",
        "%vlocity_namespace%__FilterGroup__c": 0,
        "%vlocity_namespace%__FilterOperator__c": "=",
        "%vlocity_namespace%__FilterValue__c": "Id",
        "%vlocity_namespace%__GlobalKey__c": "c4591f24-2460-82c1-fee1-77402d8efcd5",
        "%vlocity_namespace%__InterfaceFieldAPIName__c": "Id",
        "%vlocity_namespace%__InterfaceObjectLookupOrder__c": 1,
        "%vlocity_namespace%__InterfaceObjectName__c": "Order",
        "%vlocity_namespace%__IsDisabled__c": false,
        "%vlocity_namespace%__IsRequiredForUpsert__c": false,
        "%vlocity_namespace%__MapId__c": "Order Discount Extract - UpdateCustoma0Nf4000004AIjuEAGItem7",
        "%vlocity_namespace%__OMplusSyncEnabled__c": true,
        "%vlocity_namespace%__UpsertKey__c": false,
        "Name": "Order Discount Extract - Update",
        "VlocityDataPackType": "SObject",
        "VlocityRecordSObjectType": "%vlocity_namespace%__DRMapItem__c"
    },
    {
        "%vlocity_namespace%__DomainObjectAPIName__c": "json",
        "%vlocity_namespace%__DomainObjectCreationOrder__c": 0,
        "%vlocity_namespace%__DomainObjectFieldAPIName__c": "Order:FrameContract",
        "%vlocity_namespace%__FilterGroup__c": 0,
        "%vlocity_namespace%__FilterOperator__c": "=",
        "%vlocity_namespace%__FilterValue__c": "Id",
        "%vlocity_namespace%__GlobalKey__c": "cf7e781b-2a0d-4e09-f6fd-152009b9b242",
        "%vlocity_namespace%__InterfaceFieldAPIName__c": "%vlocity_namespace%__OrderId__c",
        "%vlocity_namespace%__InterfaceObjectLookupOrder__c": 2,
        "%vlocity_namespace%__InterfaceObjectName__c": "Contract",
        "%vlocity_namespace%__IsDisabled__c": false,
        "%vlocity_namespace%__IsRequiredForUpsert__c": false,
        "%vlocity_namespace%__MapId__c": "Order Discount Extract - UpdateCustoma0Nf4000004AIjuEAGItem6",
        "%vlocity_namespace%__OMplusSyncEnabled__c": true,
        "%vlocity_namespace%__UpsertKey__c": false,
        "Name": "Order Discount Extract - Update",
        "VlocityDataPackType": "SObject",
        "VlocityRecordSObjectType": "%vlocity_namespace%__DRMapItem__c"
    },
    {
        "%vlocity_namespace%__DomainObjectAPIName__c": "json",
        "%vlocity_namespace%__DomainObjectCreationOrder__c": 0,
        "%vlocity_namespace%__DomainObjectFieldAPIName__c": "Order:FrameContract",
        "%vlocity_namespace%__FilterGroup__c": 0,
        "%vlocity_namespace%__FilterOperator__c": "=",
        "%vlocity_namespace%__FilterValue__c": "'Draft'",
        "%vlocity_namespace%__GlobalKey__c": "3dd2b7c7-c876-cde5-a704-ff32bba7012b",
        "%vlocity_namespace%__InterfaceFieldAPIName__c": "Status",
        "%vlocity_namespace%__InterfaceObjectLookupOrder__c": 2,
        "%vlocity_namespace%__InterfaceObjectName__c": "Contract",
        "%vlocity_namespace%__IsDisabled__c": false,
        "%vlocity_namespace%__IsRequiredForUpsert__c": false,
        "%vlocity_namespace%__MapId__c": "Order Discount Extract - UpdateCustoma0Nf4000004AIjuEAGItem9",
        "%vlocity_namespace%__OMplusSyncEnabled__c": true,
        "%vlocity_namespace%__UpsertKey__c": false,
        "Name": "Order Discount Extract - Update",
        "VlocityDataPackType": "SObject",
        "VlocityRecordSObjectType": "%vlocity_namespace%__DRMapItem__c"
    },
    {
        "%vlocity_namespace%__DomainObjectAPIName__c": "json",
        "%vlocity_namespace%__DomainObjectCreationOrder__c": 0,
        "%vlocity_namespace%__DomainObjectFieldAPIName__c": "Order:FrameContract:Version",
        "%vlocity_namespace%__FilterGroup__c": 0,
        "%vlocity_namespace%__FilterOperator__c": "=",
        "%vlocity_namespace%__FilterValue__c": "Order:FrameContract:Id",
        "%vlocity_namespace%__GlobalKey__c": "5e664e1b-d9c8-ae10-ba29-b02965afca0d",
        "%vlocity_namespace%__InterfaceFieldAPIName__c": "%vlocity_namespace%__ContractId__c",
        "%vlocity_namespace%__InterfaceObjectLookupOrder__c": 3,
        "%vlocity_namespace%__InterfaceObjectName__c": "%vlocity_namespace%__ContractVersion__c",
        "%vlocity_namespace%__IsDisabled__c": false,
        "%vlocity_namespace%__IsRequiredForUpsert__c": false,
        "%vlocity_namespace%__MapId__c": "Order Discount Extract - UpdateCustom6906",
        "%vlocity_namespace%__OMplusSyncEnabled__c": true,
        "%vlocity_namespace%__UpsertKey__c": false,
        "Name": "Order Discount Extract - Update",
        "VlocityDataPackType": "SObject",
        "VlocityRecordSObjectType": "%vlocity_namespace%__DRMapItem__c"
    },
    {
        "%vlocity_namespace%__DomainObjectAPIName__c": "json",
        "%vlocity_namespace%__DomainObjectCreationOrder__c": 0,
        "%vlocity_namespace%__DomainObjectFieldAPIName__c": "Order:FrameContract:Version",
        "%vlocity_namespace%__FilterGroup__c": 0,
        "%vlocity_namespace%__FilterOperator__c": "=",
        "%vlocity_namespace%__FilterValue__c": "'Active'",
        "%vlocity_namespace%__GlobalKey__c": "159b0dfe-4e71-b3ff-240b-074b2b0bb533",
        "%vlocity_namespace%__InterfaceFieldAPIName__c": "%vlocity_namespace%__Status__c",
        "%vlocity_namespace%__InterfaceObjectLookupOrder__c": 3,
        "%vlocity_namespace%__InterfaceObjectName__c": "%vlocity_namespace%__ContractVersion__c",
        "%vlocity_namespace%__IsDisabled__c": false,
        "%vlocity_namespace%__IsRequiredForUpsert__c": false,
        "%vlocity_namespace%__MapId__c": "Order Discount Extract - UpdateCustom1932",
        "%vlocity_namespace%__OMplusSyncEnabled__c": true,
        "%vlocity_namespace%__UpsertKey__c": false,
        "Name": "Order Discount Extract - Update",
        "VlocityDataPackType": "SObject",
        "VlocityRecordSObjectType": "%vlocity_namespace%__DRMapItem__c"
    },
    {
        "%vlocity_namespace%__DomainObjectAPIName__c": "json",
        "%vlocity_namespace%__DomainObjectCreationOrder__c": 0,
        "%vlocity_namespace%__DomainObjectFieldAPIName__c": "Order:FrameContract:Version:Discount",
        "%vlocity_namespace%__FilterGroup__c": 0,
        "%vlocity_namespace%__FilterOperator__c": "<>",
        "%vlocity_namespace%__FilterValue__c": "'Deactivate'",
        "%vlocity_namespace%__GlobalKey__c": "35758695-34e7-602a-36ed-97b1a6d453e8",
        "%vlocity_namespace%__InterfaceFieldAPIName__c": "%vlocity_namespace%__Action__c",
        "%vlocity_namespace%__InterfaceObjectLookupOrder__c": 4,
        "%vlocity_namespace%__InterfaceObjectName__c": "%vlocity_namespace%__OrderDiscount__c",
        "%vlocity_namespace%__IsDisabled__c": false,
        "%vlocity_namespace%__IsRequiredForUpsert__c": false,
        "%vlocity_namespace%__MapId__c": "Order Discount Extract - UpdateCustom789",
        "%vlocity_namespace%__OMplusSyncEnabled__c": true,
        "%vlocity_namespace%__UpsertKey__c": false,
        "Name": "Order Discount Extract - Update",
        "VlocityDataPackType": "SObject",
        "VlocityRecordSObjectType": "%vlocity_namespace%__DRMapItem__c"
    },
    {
        "%vlocity_namespace%__DomainObjectAPIName__c": "json",
        "%vlocity_namespace%__DomainObjectCreationOrder__c": 0,
        "%vlocity_namespace%__DomainObjectFieldAPIName__c": "Order:FrameContract:Version:Discount",
        "%vlocity_namespace%__FilterGroup__c": 0,
        "%vlocity_namespace%__FilterOperator__c": "=",
        "%vlocity_namespace%__FilterValue__c": "'Approved'",
        "%vlocity_namespace%__GlobalKey__c": "99ac16f9-02b6-9809-0ab3-39d701b7c78e",
        "%vlocity_namespace%__InterfaceFieldAPIName__c": "%vlocity_namespace%__ApprovalStatus__c",
        "%vlocity_namespace%__InterfaceObjectLookupOrder__c": 4,
        "%vlocity_namespace%__InterfaceObjectName__c": "%vlocity_namespace%__OrderDiscount__c",
        "%vlocity_namespace%__IsDisabled__c": false,
        "%vlocity_namespace%__IsRequiredForUpsert__c": false,
        "%vlocity_namespace%__MapId__c": "Order Discount Extract - UpdateCustom3942",
        "%vlocity_namespace%__OMplusSyncEnabled__c": true,
        "%vlocity_namespace%__UpsertKey__c": false,
        "Name": "Order Discount Extract - Update",
        "VlocityDataPackType": "SObject",
        "VlocityRecordSObjectType": "%vlocity_namespace%__DRMapItem__c"
    },
    {
        "%vlocity_namespace%__DomainObjectAPIName__c": "json",
        "%vlocity_namespace%__DomainObjectCreationOrder__c": 0,
        "%vlocity_namespace%__DomainObjectFieldAPIName__c": "Order:FrameContract:Version:Discount",
        "%vlocity_namespace%__FilterGroup__c": 0,
        "%vlocity_namespace%__FilterOperator__c": "=",
        "%vlocity_namespace%__FilterValue__c": "'Contract'",
        "%vlocity_namespace%__GlobalKey__c": "71eb80ee-80f3-40c6-4e92-3cf686e002e9",
        "%vlocity_namespace%__InterfaceFieldAPIName__c": "%vlocity_namespace%__DiscountType__c",
        "%vlocity_namespace%__InterfaceObjectLookupOrder__c": 4,
        "%vlocity_namespace%__InterfaceObjectName__c": "%vlocity_namespace%__OrderDiscount__c",
        "%vlocity_namespace%__IsDisabled__c": false,
        "%vlocity_namespace%__IsRequiredForUpsert__c": false,
        "%vlocity_namespace%__MapId__c": "Order Discount Extract - UpdateCustom4372",
        "%vlocity_namespace%__OMplusSyncEnabled__c": true,
        "%vlocity_namespace%__UpsertKey__c": false,
        "Name": "Order Discount Extract - Update",
        "VlocityDataPackType": "SObject",
        "VlocityRecordSObjectType": "%vlocity_namespace%__DRMapItem__c"
    },
    {
        "%vlocity_namespace%__DomainObjectAPIName__c": "json",
        "%vlocity_namespace%__DomainObjectCreationOrder__c": 0,
        "%vlocity_namespace%__DomainObjectFieldAPIName__c": "Order:FrameContract:Version:Discount",
        "%vlocity_namespace%__FilterGroup__c": 0,
        "%vlocity_namespace%__FilterOperator__c": "=",
        "%vlocity_namespace%__FilterValue__c": "Id",
        "%vlocity_namespace%__GlobalKey__c": "6c059abf-d1a3-cfe4-cb2f-ce5ee65483f6",
        "%vlocity_namespace%__InterfaceFieldAPIName__c": "%vlocity_namespace%__OrderId__c",
        "%vlocity_namespace%__InterfaceObjectLookupOrder__c": 4,
        "%vlocity_namespace%__InterfaceObjectName__c": "%vlocity_namespace%__OrderDiscount__c",
        "%vlocity_namespace%__IsDisabled__c": false,
        "%vlocity_namespace%__IsRequiredForUpsert__c": false,
        "%vlocity_namespace%__MapId__c": "Order Discount Extract - UpdateCustom7693",
        "%vlocity_namespace%__OMplusSyncEnabled__c": true,
        "%vlocity_namespace%__UpsertKey__c": false,
        "Name": "Order Discount Extract - Update",
        "VlocityDataPackType": "SObject",
        "VlocityRecordSObjectType": "%vlocity_namespace%__DRMapItem__c"
    },
    {
        "%vlocity_namespace%__DomainObjectAPIName__c": "json",
        "%vlocity_namespace%__DomainObjectCreationOrder__c": 0,
        "%vlocity_namespace%__DomainObjectFieldAPIName__c": "Order:FrameContract:Version:Discount:DiscountItem",
        "%vlocity_namespace%__FilterGroup__c": 0,
        "%vlocity_namespace%__FilterOperator__c": "=",
        "%vlocity_namespace%__FilterValue__c": "Order:FrameContract:Version:Discount:Id",
        "%vlocity_namespace%__GlobalKey__c": "a243c283-826b-a8b2-fd1a-9a1dbe8d5df1",
        "%vlocity_namespace%__InterfaceFieldAPIName__c": "%vlocity_namespace%__OrderDiscountId__c",
        "%vlocity_namespace%__InterfaceObjectLookupOrder__c": 5,
        "%vlocity_namespace%__InterfaceObjectName__c": "%vlocity_namespace%__OrderDiscountItem__c",
        "%vlocity_namespace%__IsDisabled__c": false,
        "%vlocity_namespace%__IsRequiredForUpsert__c": false,
        "%vlocity_namespace%__MapId__c": "Order Discount Extract - UpdateCustoma0Nf4000004AIjuEAGItem1",
        "%vlocity_namespace%__OMplusSyncEnabled__c": true,
        "%vlocity_namespace%__UpsertKey__c": false,
        "Name": "Order Discount Extract - Update",
        "VlocityDataPackType": "SObject",
        "VlocityRecordSObjectType": "%vlocity_namespace%__DRMapItem__c"
    },
    {
        "%vlocity_namespace%__DomainObjectAPIName__c": "json",
        "%vlocity_namespace%__DomainObjectCreationOrder__c": 0,
        "%vlocity_namespace%__DomainObjectFieldAPIName__c": "Order:FrameContract:Version:Discount:DiscountPricing",
        "%vlocity_namespace%__FilterGroup__c": 0,
        "%vlocity_namespace%__FilterOperator__c": "=",
        "%vlocity_namespace%__FilterValue__c": "Order:FrameContract:Version:Discount:Id",
        "%vlocity_namespace%__GlobalKey__c": "9316f30e-9e56-3fd8-3113-62591b43aaa5",
        "%vlocity_namespace%__InterfaceFieldAPIName__c": "%vlocity_namespace%__OrderDiscountId__c",
        "%vlocity_namespace%__InterfaceObjectLookupOrder__c": 6,
        "%vlocity_namespace%__InterfaceObjectName__c": "%vlocity_namespace%__OrderDiscountPricing__c",
        "%vlocity_namespace%__IsDisabled__c": false,
        "%vlocity_namespace%__IsRequiredForUpsert__c": false,
        "%vlocity_namespace%__MapId__c": "Order Discount Extract - UpdateCustoma0Nf4000004AIjuEAGItem2",
        "%vlocity_namespace%__OMplusSyncEnabled__c": true,
        "%vlocity_namespace%__UpsertKey__c": false,
        "Name": "Order Discount Extract - Update",
        "VlocityDataPackType": "SObject",
        "VlocityRecordSObjectType": "%vlocity_namespace%__DRMapItem__c"
    },
    {
        "%vlocity_namespace%__DomainObjectAPIName__c": "json",
        "%vlocity_namespace%__DomainObjectCreationOrder__c": 0,
        "%vlocity_namespace%__DomainObjectFieldAPIName__c": "Order:DeactivatedDiscounts",
        "%vlocity_namespace%__FilterGroup__c": 0,
        "%vlocity_namespace%__FilterOperator__c": "=",
        "%vlocity_namespace%__FilterValue__c": "'Deactivate'",
        "%vlocity_namespace%__GlobalKey__c": "cd3bc478-5654-fb7c-1f88-9677c6e95438",
        "%vlocity_namespace%__InterfaceFieldAPIName__c": "%vlocity_namespace%__Action__c",
        "%vlocity_namespace%__InterfaceObjectLookupOrder__c": 7,
        "%vlocity_namespace%__InterfaceObjectName__c": "%vlocity_namespace%__OrderDiscount__c",
        "%vlocity_namespace%__IsDisabled__c": false,
        "%vlocity_namespace%__IsRequiredForUpsert__c": false,
        "%vlocity_namespace%__MapId__c": "Order Discount Extract - UpdateCustom2629",
        "%vlocity_namespace%__OMplusSyncEnabled__c": true,
        "%vlocity_namespace%__UpsertKey__c": false,
        "Name": "Order Discount Extract - Update",
        "VlocityDataPackType": "SObject",
        "VlocityRecordSObjectType": "%vlocity_namespace%__DRMapItem__c"
    },
    {
        "%vlocity_namespace%__DomainObjectAPIName__c": "json",
        "%vlocity_namespace%__DomainObjectCreationOrder__c": 0,
        "%vlocity_namespace%__DomainObjectFieldAPIName__c": "Order:DeactivatedDiscounts",
        "%vlocity_namespace%__FilterGroup__c": 0,
        "%vlocity_namespace%__FilterOperator__c": "=",
        "%vlocity_namespace%__FilterValue__c": "'Approved'",
        "%vlocity_namespace%__GlobalKey__c": "d51d31c2-e679-5f06-396e-3038bd9c48a5",
        "%vlocity_namespace%__InterfaceFieldAPIName__c": "%vlocity_namespace%__ApprovalStatus__c",
        "%vlocity_namespace%__InterfaceObjectLookupOrder__c": 7,
        "%vlocity_namespace%__InterfaceObjectName__c": "%vlocity_namespace%__OrderDiscount__c",
        "%vlocity_namespace%__IsDisabled__c": false,
        "%vlocity_namespace%__IsRequiredForUpsert__c": false,
        "%vlocity_namespace%__MapId__c": "Order Discount Extract - UpdateCustom5140",
        "%vlocity_namespace%__OMplusSyncEnabled__c": true,
        "%vlocity_namespace%__UpsertKey__c": false,
        "Name": "Order Discount Extract - Update",
        "VlocityDataPackType": "SObject",
        "VlocityRecordSObjectType": "%vlocity_namespace%__DRMapItem__c"
    },
    {
        "%vlocity_namespace%__DomainObjectAPIName__c": "json",
        "%vlocity_namespace%__DomainObjectCreationOrder__c": 0,
        "%vlocity_namespace%__DomainObjectFieldAPIName__c": "Order:DeactivatedDiscounts",
        "%vlocity_namespace%__FilterGroup__c": 0,
        "%vlocity_namespace%__FilterOperator__c": "=",
        "%vlocity_namespace%__FilterValue__c": "'Contract'",
        "%vlocity_namespace%__GlobalKey__c": "33dfd3a4-3be2-9628-466a-4e429c4616be",
        "%vlocity_namespace%__InterfaceFieldAPIName__c": "%vlocity_namespace%__DiscountType__c",
        "%vlocity_namespace%__InterfaceObjectLookupOrder__c": 7,
        "%vlocity_namespace%__InterfaceObjectName__c": "%vlocity_namespace%__OrderDiscount__c",
        "%vlocity_namespace%__IsDisabled__c": false,
        "%vlocity_namespace%__IsRequiredForUpsert__c": false,
        "%vlocity_namespace%__MapId__c": "Order Discount Extract - UpdateCustom8517",
        "%vlocity_namespace%__OMplusSyncEnabled__c": true,
        "%vlocity_namespace%__UpsertKey__c": false,
        "Name": "Order Discount Extract - Update",
        "VlocityDataPackType": "SObject",
        "VlocityRecordSObjectType": "%vlocity_namespace%__DRMapItem__c"
    },
    {
        "%vlocity_namespace%__DomainObjectAPIName__c": "json",
        "%vlocity_namespace%__DomainObjectCreationOrder__c": 0,
        "%vlocity_namespace%__DomainObjectFieldAPIName__c": "Order:DeactivatedDiscounts",
        "%vlocity_namespace%__FilterGroup__c": 0,
        "%vlocity_namespace%__FilterOperator__c": "=",
        "%vlocity_namespace%__FilterValue__c": "''",
        "%vlocity_namespace%__GlobalKey__c": "d8c2112e-9b36-eacf-8541-f71ca035ea85",
        "%vlocity_namespace%__InterfaceFieldAPIName__c": "%vlocity_namespace%__EffectiveEndDate__c",
        "%vlocity_namespace%__InterfaceObjectLookupOrder__c": 7,
        "%vlocity_namespace%__InterfaceObjectName__c": "%vlocity_namespace%__OrderDiscount__c",
        "%vlocity_namespace%__IsDisabled__c": false,
        "%vlocity_namespace%__IsRequiredForUpsert__c": false,
        "%vlocity_namespace%__MapId__c": "Order Discount Extract - UpdateCustom6009",
        "%vlocity_namespace%__OMplusSyncEnabled__c": true,
        "%vlocity_namespace%__UpsertKey__c": false,
        "Name": "Order Discount Extract - Update",
        "VlocityDataPackType": "SObject",
        "VlocityRecordSObjectType": "%vlocity_namespace%__DRMapItem__c"
    },
    {
        "%vlocity_namespace%__DomainObjectAPIName__c": "json",
        "%vlocity_namespace%__DomainObjectCreationOrder__c": 0,
        "%vlocity_namespace%__DomainObjectFieldAPIName__c": "Order:DeactivatedDiscounts",
        "%vlocity_namespace%__FilterGroup__c": 0,
        "%vlocity_namespace%__FilterOperator__c": "=",
        "%vlocity_namespace%__FilterValue__c": "Id",
        "%vlocity_namespace%__GlobalKey__c": "58e6f5a1-1a2e-13e2-7538-0cd192bdf26a",
        "%vlocity_namespace%__InterfaceFieldAPIName__c": "%vlocity_namespace%__OrderId__c",
        "%vlocity_namespace%__InterfaceObjectLookupOrder__c": 7,
        "%vlocity_namespace%__InterfaceObjectName__c": "%vlocity_namespace%__OrderDiscount__c",
        "%vlocity_namespace%__IsDisabled__c": false,
        "%vlocity_namespace%__IsRequiredForUpsert__c": false,
        "%vlocity_namespace%__MapId__c": "Order Discount Extract - UpdateCustom8650",
        "%vlocity_namespace%__OMplusSyncEnabled__c": true,
        "%vlocity_namespace%__UpsertKey__c": false,
        "Name": "Order Discount Extract - Update",
        "VlocityDataPackType": "SObject",
        "VlocityRecordSObjectType": "%vlocity_namespace%__DRMapItem__c"
    },
    {
        "%vlocity_namespace%__DomainObjectAPIName__c": "Formula",
        "%vlocity_namespace%__DomainObjectCreationOrder__c": 0,
        "%vlocity_namespace%__DomainObjectFieldAPIName__c": "Formula",
        "%vlocity_namespace%__FormulaOrder__c": 1,
        "%vlocity_namespace%__FormulaResultPath__c": "FrameContractCount",
        "%vlocity_namespace%__Formula__c": "COUNTQUERY(\"SELECT count() FROM Contract WHERE OrderId__c = '{0}' AND Status = 'Draft'\",  Order:Id)",
        "%vlocity_namespace%__GlobalKey__c": "dab440ad-08fd-5fa5-19e7-961f4736347e",
        "%vlocity_namespace%__IsDisabled__c": false,
        "%vlocity_namespace%__IsRequiredForUpsert__c": false,
        "%vlocity_namespace%__MapId__c": "Order Discount Extract - UpdateCustoma0Nf4000004AIjuEAGItem0",
        "%vlocity_namespace%__OMplusSyncEnabled__c": true,
        "%vlocity_namespace%__UpsertKey__c": false,
        "Name": "Order Discount Extract - Update",
        "VlocityDataPackType": "SObject",
        "VlocityRecordSObjectType": "%vlocity_namespace%__DRMapItem__c"
    },
    {
        "%vlocity_namespace%__DomainObjectAPIName__c": "json",
        "%vlocity_namespace%__DomainObjectCreationOrder__c": 1,
        "%vlocity_namespace%__DomainObjectFieldAPIName__c": "Order:AccountId",
        "%vlocity_namespace%__GlobalKey__c": "db05bb97-20f1-8d8c-23ba-d6c0745644ee",
        "%vlocity_namespace%__InterfaceFieldAPIName__c": "Order:AccountId",
        "%vlocity_namespace%__IsDisabled__c": false,
        "%vlocity_namespace%__IsRequiredForUpsert__c": false,
        "%vlocity_namespace%__MapId__c": "Order Discount Extract - UpdateCustoma0Nf4000004AIjuEAGItem11",
        "%vlocity_namespace%__OMplusSyncEnabled__c": true,
        "%vlocity_namespace%__UpsertKey__c": false,
        "Name": "Order Discount Extract - Update",
        "VlocityDataPackType": "SObject",
        "VlocityRecordSObjectType": "%vlocity_namespace%__DRMapItem__c"
    },
    {
        "%vlocity_namespace%__DomainObjectAPIName__c": "json",
        "%vlocity_namespace%__DomainObjectCreationOrder__c": 1,
        "%vlocity_namespace%__DomainObjectFieldAPIName__c": "Order:DeactivatedDiscounts:EffectiveEndDate",
        "%vlocity_namespace%__GlobalKey__c": "deb0156b-e7d9-e8c1-2416-5bf9a9577aa7",
        "%vlocity_namespace%__InterfaceFieldAPIName__c": "Order:DeactivatedDiscounts:%vlocity_namespace%__EffectiveEndDate__c",
        "%vlocity_namespace%__IsDisabled__c": false,
        "%vlocity_namespace%__IsRequiredForUpsert__c": false,
        "%vlocity_namespace%__MapId__c": "Order Discount Extract - UpdateCustom4051",
        "%vlocity_namespace%__OMplusSyncEnabled__c": true,
        "%vlocity_namespace%__UpsertKey__c": false,
        "Name": "Order Discount Extract - Update",
        "VlocityDataPackType": "SObject",
        "VlocityRecordSObjectType": "%vlocity_namespace%__DRMapItem__c"
    },
    {
        "%vlocity_namespace%__DomainObjectAPIName__c": "json",
        "%vlocity_namespace%__DomainObjectCreationOrder__c": 1,
        "%vlocity_namespace%__DomainObjectFieldAPIName__c": "Order:DeactivatedDiscounts:Id",
        "%vlocity_namespace%__GlobalKey__c": "aed3561d-1cee-892c-0e91-9a1fcc68e538",
        "%vlocity_namespace%__InterfaceFieldAPIName__c": "Order:DeactivatedDiscounts:Id",
        "%vlocity_namespace%__IsDisabled__c": false,
        "%vlocity_namespace%__IsRequiredForUpsert__c": false,
        "%vlocity_namespace%__MapId__c": "Order Discount Extract - UpdateCustom6432",
        "%vlocity_namespace%__OMplusSyncEnabled__c": true,
        "%vlocity_namespace%__UpsertKey__c": false,
        "Name": "Order Discount Extract - Update",
        "VlocityDataPackType": "SObject",
        "VlocityRecordSObjectType": "%vlocity_namespace%__DRMapItem__c"
    },
    {
        "%vlocity_namespace%__DomainObjectAPIName__c": "json",
        "%vlocity_namespace%__DomainObjectCreationOrder__c": 1,
        "%vlocity_namespace%__DomainObjectFieldAPIName__c": "Order:FrameContract:EndDate",
        "%vlocity_namespace%__GlobalKey__c": "5f39baff-da0e-180c-340e-2ef683ac0e7f",
        "%vlocity_namespace%__InterfaceFieldAPIName__c": "Order:FrameContract:EndDate",
        "%vlocity_namespace%__IsDisabled__c": false,
        "%vlocity_namespace%__IsRequiredForUpsert__c": false,
        "%vlocity_namespace%__MapId__c": "Order Discount Extract - UpdateCustom8224",
        "%vlocity_namespace%__OMplusSyncEnabled__c": true,
        "%vlocity_namespace%__UpsertKey__c": false,
        "Name": "Order Discount Extract - Update",
        "VlocityDataPackType": "SObject",
        "VlocityRecordSObjectType": "%vlocity_namespace%__DRMapItem__c"
    },
    {
        "%vlocity_namespace%__DomainObjectAPIName__c": "json",
        "%vlocity_namespace%__DomainObjectCreationOrder__c": 1,
        "%vlocity_namespace%__DomainObjectFieldAPIName__c": "Order:FrameContract:Id",
        "%vlocity_namespace%__GlobalKey__c": "1d9e266e-cb9f-c87b-365a-cfc00c5755af",
        "%vlocity_namespace%__InterfaceFieldAPIName__c": "Order:FrameContract:Id",
        "%vlocity_namespace%__IsDisabled__c": false,
        "%vlocity_namespace%__IsRequiredForUpsert__c": false,
        "%vlocity_namespace%__MapId__c": "Order Discount Extract - UpdateCustoma0Nf4000004AIjuEAGItem31",
        "%vlocity_namespace%__OMplusSyncEnabled__c": true,
        "%vlocity_namespace%__UpsertKey__c": false,
        "Name": "Order Discount Extract - Update",
        "VlocityDataPackType": "SObject",
        "VlocityRecordSObjectType": "%vlocity_namespace%__DRMapItem__c"
    },
    {
        "%vlocity_namespace%__DomainObjectAPIName__c": "json",
        "%vlocity_namespace%__DomainObjectCreationOrder__c": 1,
        "%vlocity_namespace%__DomainObjectFieldAPIName__c": "Order:FrameContract:StartDate",
        "%vlocity_namespace%__GlobalKey__c": "3ed965b9-08d5-646f-c1a4-6e4a9b2fa632",
        "%vlocity_namespace%__InterfaceFieldAPIName__c": "Order:FrameContract:StartDate",
        "%vlocity_namespace%__IsDisabled__c": false,
        "%vlocity_namespace%__IsRequiredForUpsert__c": false,
        "%vlocity_namespace%__MapId__c": "Order Discount Extract - UpdateCustom9837",
        "%vlocity_namespace%__OMplusSyncEnabled__c": true,
        "%vlocity_namespace%__UpsertKey__c": false,
        "Name": "Order Discount Extract - Update",
        "VlocityDataPackType": "SObject",
        "VlocityRecordSObjectType": "%vlocity_namespace%__DRMapItem__c"
    },
    {
        "%vlocity_namespace%__DomainObjectAPIName__c": "json",
        "%vlocity_namespace%__DomainObjectCreationOrder__c": 1,
        "%vlocity_namespace%__DomainObjectFieldAPIName__c": "Order:FrameContract:Status",
        "%vlocity_namespace%__GlobalKey__c": "b83c4285-325e-6ed8-5750-8b5f63ec6c28",
        "%vlocity_namespace%__InterfaceFieldAPIName__c": "Order:FrameContract:Status",
        "%vlocity_namespace%__IsDisabled__c": false,
        "%vlocity_namespace%__IsRequiredForUpsert__c": false,
        "%vlocity_namespace%__MapId__c": "Order Discount Extract - UpdateCustoma0Nf4000004AIjuEAGItem32",
        "%vlocity_namespace%__OMplusSyncEnabled__c": true,
        "%vlocity_namespace%__UpsertKey__c": false,
        "Name": "Order Discount Extract - Update",
        "VlocityDataPackType": "SObject",
        "VlocityRecordSObjectType": "%vlocity_namespace%__DRMapItem__c"
    },
    {
        "%vlocity_namespace%__DomainObjectAPIName__c": "json",
        "%vlocity_namespace%__DomainObjectCreationOrder__c": 1,
        "%vlocity_namespace%__DomainObjectFieldAPIName__c": "Order:FrameContract:Version:Discount:AppliesToAllItems",
        "%vlocity_namespace%__GlobalKey__c": "dc4207d2-664b-0c01-7e42-3b42bc03d46c",
        "%vlocity_namespace%__InterfaceFieldAPIName__c": "Order:FrameContract:Version:Discount:%vlocity_namespace%__AppliesToAllItems__c",
        "%vlocity_namespace%__IsDisabled__c": false,
        "%vlocity_namespace%__IsRequiredForUpsert__c": false,
        "%vlocity_namespace%__MapId__c": "Order Discount Extract - UpdateCustom8585",
        "%vlocity_namespace%__OMplusSyncEnabled__c": true,
        "%vlocity_namespace%__UpsertKey__c": false,
        "Name": "Order Discount Extract - Update",
        "VlocityDataPackType": "SObject",
        "VlocityRecordSObjectType": "%vlocity_namespace%__DRMapItem__c"
    },
    {
        "%vlocity_namespace%__DomainObjectAPIName__c": "json",
        "%vlocity_namespace%__DomainObjectCreationOrder__c": 1,
        "%vlocity_namespace%__DomainObjectFieldAPIName__c": "Order:FrameContract:Version:Discount:Description",
        "%vlocity_namespace%__GlobalKey__c": "68de3d04-cd9f-e15a-3a3d-456ca42e080e",
        "%vlocity_namespace%__InterfaceFieldAPIName__c": "Order:FrameContract:Version:Discount:%vlocity_namespace%__Description__c",
        "%vlocity_namespace%__IsDisabled__c": false,
        "%vlocity_namespace%__IsRequiredForUpsert__c": false,
        "%vlocity_namespace%__MapId__c": "Order Discount Extract - UpdateCustoma0Nf4000004AIjuEAGItem13",
        "%vlocity_namespace%__OMplusSyncEnabled__c": true,
        "%vlocity_namespace%__UpsertKey__c": false,
        "Name": "Order Discount Extract - Update",
        "VlocityDataPackType": "SObject",
        "VlocityRecordSObjectType": "%vlocity_namespace%__DRMapItem__c"
    },
    {
        "%vlocity_namespace%__DomainObjectAPIName__c": "json",
        "%vlocity_namespace%__DomainObjectCreationOrder__c": 1,
        "%vlocity_namespace%__DomainObjectFieldAPIName__c": "Order:FrameContract:Version:Discount:DiscountItem:CatalogCategoryId",
        "%vlocity_namespace%__GlobalKey__c": "3d8188b5-51f5-905b-ed00-b84767c4c333",
        "%vlocity_namespace%__InterfaceFieldAPIName__c": "Order:FrameContract:Version:Discount:DiscountItem:%vlocity_namespace%__CatalogCategoryId__c",
        "%vlocity_namespace%__IsDisabled__c": false,
        "%vlocity_namespace%__IsRequiredForUpsert__c": false,
        "%vlocity_namespace%__MapId__c": "Order Discount Extract - UpdateCustoma0Nf4000004AIjuEAGItem18",
        "%vlocity_namespace%__OMplusSyncEnabled__c": true,
        "%vlocity_namespace%__UpsertKey__c": false,
        "Name": "Order Discount Extract - Update",
        "VlocityDataPackType": "SObject",
        "VlocityRecordSObjectType": "%vlocity_namespace%__DRMapItem__c"
    },
    {
        "%vlocity_namespace%__DomainObjectAPIName__c": "json",
        "%vlocity_namespace%__DomainObjectCreationOrder__c": 1,
        "%vlocity_namespace%__DomainObjectFieldAPIName__c": "Order:FrameContract:Version:Discount:DiscountItem:Description",
        "%vlocity_namespace%__GlobalKey__c": "eec28afc-5a8d-5f34-a3bb-23e74196d12d",
        "%vlocity_namespace%__InterfaceFieldAPIName__c": "Order:FrameContract:Version:Discount:DiscountItem:%vlocity_namespace%__Description__c",
        "%vlocity_namespace%__IsDisabled__c": false,
        "%vlocity_namespace%__IsRequiredForUpsert__c": false,
        "%vlocity_namespace%__MapId__c": "Order Discount Extract - UpdateCustoma0Nf4000004AIjuEAGItem19",
        "%vlocity_namespace%__OMplusSyncEnabled__c": true,
        "%vlocity_namespace%__UpsertKey__c": false,
        "Name": "Order Discount Extract - Update",
        "VlocityDataPackType": "SObject",
        "VlocityRecordSObjectType": "%vlocity_namespace%__DRMapItem__c"
    },
    {
        "%vlocity_namespace%__DomainObjectAPIName__c": "json",
        "%vlocity_namespace%__DomainObjectCreationOrder__c": 1,
        "%vlocity_namespace%__DomainObjectFieldAPIName__c": "Order:FrameContract:Version:Discount:DiscountItem:Name",
        "%vlocity_namespace%__GlobalKey__c": "8921a1b3-3679-2480-d022-50947d51f5db",
        "%vlocity_namespace%__InterfaceFieldAPIName__c": "Order:FrameContract:Version:Discount:DiscountItem:Name",
        "%vlocity_namespace%__IsDisabled__c": false,
        "%vlocity_namespace%__IsRequiredForUpsert__c": false,
        "%vlocity_namespace%__MapId__c": "Order Discount Extract - UpdateCustoma0Nf4000004AIjuEAGItem22",
        "%vlocity_namespace%__OMplusSyncEnabled__c": true,
        "%vlocity_namespace%__UpsertKey__c": false,
        "Name": "Order Discount Extract - Update",
        "VlocityDataPackType": "SObject",
        "VlocityRecordSObjectType": "%vlocity_namespace%__DRMapItem__c"
    },
    {
        "%vlocity_namespace%__DomainObjectAPIName__c": "json",
        "%vlocity_namespace%__DomainObjectCreationOrder__c": 1,
        "%vlocity_namespace%__DomainObjectFieldAPIName__c": "Order:FrameContract:Version:Discount:DiscountItem:ProductId",
        "%vlocity_namespace%__GlobalKey__c": "48b92d95-c1c6-2869-40b3-25fd9d0a1c78",
        "%vlocity_namespace%__InterfaceFieldAPIName__c": "Order:FrameContract:Version:Discount:DiscountItem:%vlocity_namespace%__ProductId__c",
        "%vlocity_namespace%__IsDisabled__c": false,
        "%vlocity_namespace%__IsRequiredForUpsert__c": false,
        "%vlocity_namespace%__MapId__c": "Order Discount Extract - UpdateCustoma0Nf4000004AIjuEAGItem20",
        "%vlocity_namespace%__OMplusSyncEnabled__c": true,
        "%vlocity_namespace%__UpsertKey__c": false,
        "Name": "Order Discount Extract - Update",
        "VlocityDataPackType": "SObject",
        "VlocityRecordSObjectType": "%vlocity_namespace%__DRMapItem__c"
    },
    {
        "%vlocity_namespace%__DomainObjectAPIName__c": "json",
        "%vlocity_namespace%__DomainObjectCreationOrder__c": 1,
        "%vlocity_namespace%__DomainObjectFieldAPIName__c": "Order:FrameContract:Version:Discount:DiscountItem:QuoteDiscountId",
        "%vlocity_namespace%__GlobalKey__c": "d5120552-37a7-ec65-df2b-f93c177f102a",
        "%vlocity_namespace%__InterfaceFieldAPIName__c": "Order:FrameContract:Version:Discount:DiscountItem:%vlocity_namespace%__QuoteDiscountId__c",
        "%vlocity_namespace%__IsDisabled__c": false,
        "%vlocity_namespace%__IsRequiredForUpsert__c": false,
        "%vlocity_namespace%__MapId__c": "Order Discount Extract - UpdateCustoma0Nf4000004AIjuEAGItem21",
        "%vlocity_namespace%__OMplusSyncEnabled__c": true,
        "%vlocity_namespace%__UpsertKey__c": false,
        "Name": "Order Discount Extract - Update",
        "VlocityDataPackType": "SObject",
        "VlocityRecordSObjectType": "%vlocity_namespace%__DRMapItem__c"
    },
    {
        "%vlocity_namespace%__DomainObjectAPIName__c": "json",
        "%vlocity_namespace%__DomainObjectCreationOrder__c": 1,
        "%vlocity_namespace%__DomainObjectFieldAPIName__c": "Order:FrameContract:Version:Discount:DiscountPricing:AdjustmentValue",
        "%vlocity_namespace%__GlobalKey__c": "ff4c0c28-84f3-b8d2-c4b0-e9c446801cfe",
        "%vlocity_namespace%__InterfaceFieldAPIName__c": "Order:FrameContract:Version:Discount:DiscountPricing:%vlocity_namespace%__AdjustmentValue__c",
        "%vlocity_namespace%__IsDisabled__c": false,
        "%vlocity_namespace%__IsRequiredForUpsert__c": false,
        "%vlocity_namespace%__MapId__c": "Order Discount Extract - UpdateCustoma0Nf4000004AIjuEAGItem23",
        "%vlocity_namespace%__OMplusSyncEnabled__c": true,
        "%vlocity_namespace%__UpsertKey__c": false,
        "Name": "Order Discount Extract - Update",
        "VlocityDataPackType": "SObject",
        "VlocityRecordSObjectType": "%vlocity_namespace%__DRMapItem__c"
    },
    {
        "%vlocity_namespace%__DomainObjectAPIName__c": "json",
        "%vlocity_namespace%__DomainObjectCreationOrder__c": 1,
        "%vlocity_namespace%__DomainObjectFieldAPIName__c": "Order:FrameContract:Version:Discount:DiscountPricing:Amount",
        "%vlocity_namespace%__GlobalKey__c": "47a851bc-fd81-50c5-1f23-47f8f81a6aaf",
        "%vlocity_namespace%__InterfaceFieldAPIName__c": "Order:FrameContract:Version:Discount:DiscountPricing:%vlocity_namespace%__Amount__c",
        "%vlocity_namespace%__IsDisabled__c": false,
        "%vlocity_namespace%__IsRequiredForUpsert__c": false,
        "%vlocity_namespace%__MapId__c": "Order Discount Extract - UpdateCustoma0Nf4000004AIjuEAGItem24",
        "%vlocity_namespace%__OMplusSyncEnabled__c": true,
        "%vlocity_namespace%__UpsertKey__c": false,
        "Name": "Order Discount Extract - Update",
        "VlocityDataPackType": "SObject",
        "VlocityRecordSObjectType": "%vlocity_namespace%__DRMapItem__c"
    },
    {
        "%vlocity_namespace%__DomainObjectAPIName__c": "json",
        "%vlocity_namespace%__DomainObjectCreationOrder__c": 1,
        "%vlocity_namespace%__DomainObjectFieldAPIName__c": "Order:FrameContract:Version:Discount:DiscountPricing:Name",
        "%vlocity_namespace%__GlobalKey__c": "0f94db56-cdab-1e93-c084-91e1935ca7c4",
        "%vlocity_namespace%__InterfaceFieldAPIName__c": "Order:FrameContract:Version:Discount:DiscountPricing:Name",
        "%vlocity_namespace%__IsDisabled__c": false,
        "%vlocity_namespace%__IsRequiredForUpsert__c": false,
        "%vlocity_namespace%__MapId__c": "Order Discount Extract - UpdateCustoma0Nf4000004AIjuEAGItem29",
        "%vlocity_namespace%__OMplusSyncEnabled__c": true,
        "%vlocity_namespace%__UpsertKey__c": false,
        "Name": "Order Discount Extract - Update",
        "VlocityDataPackType": "SObject",
        "VlocityRecordSObjectType": "%vlocity_namespace%__DRMapItem__c"
    },
    {
        "%vlocity_namespace%__DomainObjectAPIName__c": "json",
        "%vlocity_namespace%__DomainObjectCreationOrder__c": 1,
        "%vlocity_namespace%__DomainObjectFieldAPIName__c": "Order:FrameContract:Version:Discount:DiscountPricing:PricingVariableId",
        "%vlocity_namespace%__GlobalKey__c": "e52f4685-e6d5-dbd9-6961-2f30d3f668da",
        "%vlocity_namespace%__InterfaceFieldAPIName__c": "Order:FrameContract:Version:Discount:DiscountPricing:%vlocity_namespace%__PricingVariableId__c",
        "%vlocity_namespace%__IsDisabled__c": false,
        "%vlocity_namespace%__IsRequiredForUpsert__c": false,
        "%vlocity_namespace%__MapId__c": "Order Discount Extract - UpdateCustoma0Nf4000004AIjuEAGItem25",
        "%vlocity_namespace%__OMplusSyncEnabled__c": true,
        "%vlocity_namespace%__UpsertKey__c": false,
        "Name": "Order Discount Extract - Update",
        "VlocityDataPackType": "SObject",
        "VlocityRecordSObjectType": "%vlocity_namespace%__DRMapItem__c"
    },
    {
        "%vlocity_namespace%__DomainObjectAPIName__c": "json",
        "%vlocity_namespace%__DomainObjectCreationOrder__c": 1,
        "%vlocity_namespace%__DomainObjectFieldAPIName__c": "Order:FrameContract:Version:Discount:DiscountPricing:QuoteDiscountId",
        "%vlocity_namespace%__GlobalKey__c": "57772693-9c3c-bad6-a9c5-a6ada527d628",
        "%vlocity_namespace%__InterfaceFieldAPIName__c": "Order:FrameContract:Version:Discount:DiscountPricing:%vlocity_namespace%__QuoteDiscountId__c",
        "%vlocity_namespace%__IsDisabled__c": false,
        "%vlocity_namespace%__IsRequiredForUpsert__c": false,
        "%vlocity_namespace%__MapId__c": "Order Discount Extract - UpdateCustoma0Nf4000004AIjuEAGItem26",
        "%vlocity_namespace%__OMplusSyncEnabled__c": true,
        "%vlocity_namespace%__UpsertKey__c": false,
        "Name": "Order Discount Extract - Update",
        "VlocityDataPackType": "SObject",
        "VlocityRecordSObjectType": "%vlocity_namespace%__DRMapItem__c"
    },
    {
        "%vlocity_namespace%__DomainObjectAPIName__c": "json",
        "%vlocity_namespace%__DomainObjectCreationOrder__c": 1,
        "%vlocity_namespace%__DomainObjectFieldAPIName__c": "Order:FrameContract:Version:Discount:DiscountPricing:TimePlanId",
        "%vlocity_namespace%__GlobalKey__c": "510804e0-bf45-d783-dc36-7e2544436b79",
        "%vlocity_namespace%__InterfaceFieldAPIName__c": "Order:FrameContract:Version:Discount:DiscountPricing:%vlocity_namespace%__TimePlanId__c",
        "%vlocity_namespace%__IsDisabled__c": false,
        "%vlocity_namespace%__IsRequiredForUpsert__c": false,
        "%vlocity_namespace%__MapId__c": "Order Discount Extract - UpdateCustoma0Nf4000004AIjuEAGItem27",
        "%vlocity_namespace%__OMplusSyncEnabled__c": true,
        "%vlocity_namespace%__UpsertKey__c": false,
        "Name": "Order Discount Extract - Update",
        "VlocityDataPackType": "SObject",
        "VlocityRecordSObjectType": "%vlocity_namespace%__DRMapItem__c"
    },
    {
        "%vlocity_namespace%__DomainObjectAPIName__c": "json",
        "%vlocity_namespace%__DomainObjectCreationOrder__c": 1,
        "%vlocity_namespace%__DomainObjectFieldAPIName__c": "Order:FrameContract:Version:Discount:DiscountPricing:TimePolicyId",
        "%vlocity_namespace%__GlobalKey__c": "7e90953d-4d76-305e-6812-6fbd06d45b36",
        "%vlocity_namespace%__InterfaceFieldAPIName__c": "Order:FrameContract:Version:Discount:DiscountPricing:%vlocity_namespace%__TimePolicyId__c",
        "%vlocity_namespace%__IsDisabled__c": false,
        "%vlocity_namespace%__IsRequiredForUpsert__c": false,
        "%vlocity_namespace%__MapId__c": "Order Discount Extract - UpdateCustoma0Nf4000004AIjuEAGItem28",
        "%vlocity_namespace%__OMplusSyncEnabled__c": true,
        "%vlocity_namespace%__UpsertKey__c": false,
        "Name": "Order Discount Extract - Update",
        "VlocityDataPackType": "SObject",
        "VlocityRecordSObjectType": "%vlocity_namespace%__DRMapItem__c"
    },
    {
        "%vlocity_namespace%__DomainObjectAPIName__c": "json",
        "%vlocity_namespace%__DomainObjectCreationOrder__c": 1,
        "%vlocity_namespace%__DomainObjectFieldAPIName__c": "Order:FrameContract:Version:Discount:EffectiveEndDate",
        "%vlocity_namespace%__GlobalKey__c": "71b7a609-bc76-d92b-a678-bb1f41d69dd3",
        "%vlocity_namespace%__InterfaceFieldAPIName__c": "Order:FrameContract:Version:Discount:%vlocity_namespace%__EffectiveEndDate__c",
        "%vlocity_namespace%__IsDisabled__c": false,
        "%vlocity_namespace%__IsRequiredForUpsert__c": false,
        "%vlocity_namespace%__MapId__c": "Order Discount Extract - UpdateCustoma0Nf4000004AIjuEAGItem15",
        "%vlocity_namespace%__OMplusSyncEnabled__c": true,
        "%vlocity_namespace%__UpsertKey__c": false,
        "Name": "Order Discount Extract - Update",
        "VlocityDataPackType": "SObject",
        "VlocityRecordSObjectType": "%vlocity_namespace%__DRMapItem__c"
    },
    {
        "%vlocity_namespace%__DomainObjectAPIName__c": "json",
        "%vlocity_namespace%__DomainObjectCreationOrder__c": 1,
        "%vlocity_namespace%__DomainObjectFieldAPIName__c": "Order:FrameContract:Version:Discount:EffectiveStartDate",
        "%vlocity_namespace%__GlobalKey__c": "d1fc7b73-166c-1b12-d681-73385737a5c7",
        "%vlocity_namespace%__InterfaceFieldAPIName__c": "Order:FrameContract:Version:Discount:%vlocity_namespace%__EffectiveStartDate__c",
        "%vlocity_namespace%__IsDisabled__c": false,
        "%vlocity_namespace%__IsRequiredForUpsert__c": false,
        "%vlocity_namespace%__MapId__c": "Order Discount Extract - UpdateCustoma0Nf4000004AIjuEAGItem16",
        "%vlocity_namespace%__OMplusSyncEnabled__c": true,
        "%vlocity_namespace%__UpsertKey__c": false,
        "Name": "Order Discount Extract - Update",
        "VlocityDataPackType": "SObject",
        "VlocityRecordSObjectType": "%vlocity_namespace%__DRMapItem__c"
    },
    {
        "%vlocity_namespace%__DomainObjectAPIName__c": "json",
        "%vlocity_namespace%__DomainObjectCreationOrder__c": 1,
        "%vlocity_namespace%__DomainObjectFieldAPIName__c": "Order:FrameContract:Version:Discount:Name",
        "%vlocity_namespace%__GlobalKey__c": "efd3dae6-4194-1b6a-60d0-6924e92042bc",
        "%vlocity_namespace%__InterfaceFieldAPIName__c": "Order:FrameContract:Version:Discount:Name",
        "%vlocity_namespace%__IsDisabled__c": false,
        "%vlocity_namespace%__IsRequiredForUpsert__c": false,
        "%vlocity_namespace%__MapId__c": "Order Discount Extract - UpdateCustoma0Nf4000004AIjuEAGItem30",
        "%vlocity_namespace%__OMplusSyncEnabled__c": true,
        "%vlocity_namespace%__UpsertKey__c": false,
        "Name": "Order Discount Extract - Update",
        "VlocityDataPackType": "SObject",
        "VlocityRecordSObjectType": "%vlocity_namespace%__DRMapItem__c"
    },
    {
        "%vlocity_namespace%__DomainObjectAPIName__c": "json",
        "%vlocity_namespace%__DomainObjectCreationOrder__c": 1,
        "%vlocity_namespace%__DomainObjectFieldAPIName__c": "Order:FrameContract:Version:Discount:ReferenceNumber",
        "%vlocity_namespace%__GlobalKey__c": "8826a7ca-d44b-53ad-101a-36703f68329f",
        "%vlocity_namespace%__InterfaceFieldAPIName__c": "Order:FrameContract:Version:Discount:%vlocity_namespace%__ReferenceNumber__c",
        "%vlocity_namespace%__IsDisabled__c": false,
        "%vlocity_namespace%__IsRequiredForUpsert__c": false,
        "%vlocity_namespace%__MapId__c": "Order Discount Extract - UpdateCustoma0Nf4000004AIjuEAGItem17",
        "%vlocity_namespace%__OMplusSyncEnabled__c": true,
        "%vlocity_namespace%__UpsertKey__c": false,
        "Name": "Order Discount Extract - Update",
        "VlocityDataPackType": "SObject",
        "VlocityRecordSObjectType": "%vlocity_namespace%__DRMapItem__c"
    },
    {
        "%vlocity_namespace%__DomainObjectAPIName__c": "json",
        "%vlocity_namespace%__DomainObjectCreationOrder__c": 1,
        "%vlocity_namespace%__DomainObjectFieldAPIName__c": "Order:FrameContract:Version:Discount:TemplateId",
        "%vlocity_namespace%__GlobalKey__c": "8c39f19b-749f-67ef-ac92-c00123281e59",
        "%vlocity_namespace%__InterfaceFieldAPIName__c": "Order:FrameContract:Version:Discount:%vlocity_namespace%__DiscountTemplateId__c",
        "%vlocity_namespace%__IsDisabled__c": false,
        "%vlocity_namespace%__IsRequiredForUpsert__c": false,
        "%vlocity_namespace%__MapId__c": "Order Discount Extract - UpdateCustoma0Nf4000004AIjuEAGItem14",
        "%vlocity_namespace%__OMplusSyncEnabled__c": true,
        "%vlocity_namespace%__UpsertKey__c": false,
        "Name": "Order Discount Extract - Update",
        "VlocityDataPackType": "SObject",
        "VlocityRecordSObjectType": "%vlocity_namespace%__DRMapItem__c"
    },
    {
        "%vlocity_namespace%__DomainObjectAPIName__c": "json",
        "%vlocity_namespace%__DomainObjectCreationOrder__c": 1,
        "%vlocity_namespace%__DomainObjectFieldAPIName__c": "Order:FrameContract:Version:DocumentCeationSource",
        "%vlocity_namespace%__GlobalKey__c": "c3165724-4dd2-30f6-0966-a1ea8b3c48ef",
        "%vlocity_namespace%__InterfaceFieldAPIName__c": "Order:FrameContract:Version:%vlocity_namespace%__DocumentCreationSource__c",
        "%vlocity_namespace%__IsDisabled__c": false,
        "%vlocity_namespace%__IsRequiredForUpsert__c": false,
        "%vlocity_namespace%__MapId__c": "Order Discount Extract - UpdateCustom9118",
        "%vlocity_namespace%__OMplusSyncEnabled__c": true,
        "%vlocity_namespace%__UpsertKey__c": false,
        "Name": "Order Discount Extract - Update",
        "VlocityDataPackType": "SObject",
        "VlocityRecordSObjectType": "%vlocity_namespace%__DRMapItem__c"
    },
    {
        "%vlocity_namespace%__DomainObjectAPIName__c": "json",
        "%vlocity_namespace%__DomainObjectCreationOrder__c": 1,
        "%vlocity_namespace%__DomainObjectFieldAPIName__c": "Order:FrameContract:Version:DocumentTemplateId",
        "%vlocity_namespace%__GlobalKey__c": "5e22d785-2195-459b-19eb-db1e4be57546",
        "%vlocity_namespace%__InterfaceFieldAPIName__c": "Order:FrameContract:Version:%vlocity_namespace%__DocumentTemplateId__c",
        "%vlocity_namespace%__IsDisabled__c": false,
        "%vlocity_namespace%__IsRequiredForUpsert__c": false,
        "%vlocity_namespace%__MapId__c": "Order Discount Extract - UpdateCustom7691",
        "%vlocity_namespace%__OMplusSyncEnabled__c": true,
        "%vlocity_namespace%__UpsertKey__c": false,
        "Name": "Order Discount Extract - Update",
        "VlocityDataPackType": "SObject",
        "VlocityRecordSObjectType": "%vlocity_namespace%__DRMapItem__c"
    },
    {
        "%vlocity_namespace%__DomainObjectAPIName__c": "json",
        "%vlocity_namespace%__DomainObjectCreationOrder__c": 1,
        "%vlocity_namespace%__DomainObjectFieldAPIName__c": "Order:FrameContractCount",
        "%vlocity_namespace%__GlobalKey__c": "b4ba819c-4b36-a2bb-27b7-cda8e1d5c4b3",
        "%vlocity_namespace%__InterfaceFieldAPIName__c": "FrameContractCount",
        "%vlocity_namespace%__IsDisabled__c": false,
        "%vlocity_namespace%__IsRequiredForUpsert__c": false,
        "%vlocity_namespace%__MapId__c": "Order Discount Extract - UpdateCustoma0Nf4000004AIjuEAGItem10",
        "%vlocity_namespace%__OMplusSyncEnabled__c": true,
        "%vlocity_namespace%__UpsertKey__c": false,
        "Name": "Order Discount Extract - Update",
        "VlocityDataPackType": "SObject",
        "VlocityRecordSObjectType": "%vlocity_namespace%__DRMapItem__c"
    },
    {
        "%vlocity_namespace%__DomainObjectAPIName__c": "json",
        "%vlocity_namespace%__DomainObjectCreationOrder__c": 1,
        "%vlocity_namespace%__DomainObjectFieldAPIName__c": "Order:Name",
        "%vlocity_namespace%__GlobalKey__c": "472ed0a9-3bf1-7088-1f07-32ca3542e3f2",
        "%vlocity_namespace%__InterfaceFieldAPIName__c": "Order:Name",
        "%vlocity_namespace%__IsDisabled__c": false,
        "%vlocity_namespace%__IsRequiredForUpsert__c": false,
        "%vlocity_namespace%__MapId__c": "Order Discount Extract - UpdateCustoma0Nf4000004AIjuEAGItem33",
        "%vlocity_namespace%__OMplusSyncEnabled__c": true,
        "%vlocity_namespace%__UpsertKey__c": false,
        "Name": "Order Discount Extract - Update",
        "VlocityDataPackType": "SObject",
        "VlocityRecordSObjectType": "%vlocity_namespace%__DRMapItem__c"
    },
    {
        "%vlocity_namespace%__DomainObjectAPIName__c": "json",
        "%vlocity_namespace%__DomainObjectCreationOrder__c": 1,
        "%vlocity_namespace%__DomainObjectFieldAPIName__c": "Order:originalFrameContractId",
        "%vlocity_namespace%__GlobalKey__c": "373d2551-d4ad-bb62-19ef-ed875c83761c",
        "%vlocity_namespace%__InterfaceFieldAPIName__c": "Order:%vlocity_namespace%__OriginatingContractId__c",
        "%vlocity_namespace%__IsDisabled__c": false,
        "%vlocity_namespace%__IsRequiredForUpsert__c": false,
        "%vlocity_namespace%__MapId__c": "Order Discount Extract - UpdateCustoma0Nf4000004AIjuEAGItem12",
        "%vlocity_namespace%__OMplusSyncEnabled__c": true,
        "%vlocity_namespace%__UpsertKey__c": false,
        "Name": "Order Discount Extract - Update",
        "VlocityDataPackType": "SObject",
        "VlocityRecordSObjectType": "%vlocity_namespace%__DRMapItem__c"
    }
]