{
    "Body": "File_check-png.png",
    "BodyLength": 2219,
    "ContentType": "image/png",
    "Description": "",
    "DeveloperName": "CACCADACAf3d108124b914d2882c8d47a417ec0c4",
    "IsBodySearchable": false,
    "IsInternalUseOnly": false,
    "IsPublic": true,
    "Keywords": "",
    "Name": "check.png",
    "Type": "png",
    "Url": "",
    "VlocityDataPackType": "SObject",
    "VlocityRecordSObjectType": "Document",
    "VlocityRecordSourceKey": "Document/CACCADACAf3d108124b914d2882c8d47a417ec0c4"
}